[{"id":27,"annotations":[{"id":31,"completed_by":1,"result":[{"original_width":2480,"original_height":3509,"image_rotation":0,"value":{"x":5.273437500000001,"y":3.448275862068966,"width":38.28125,"height":9.793103448275865,"rotation":0,"rectanglelabels":["other"]},"id":"2i03uSqJD3","from_name":"label","to_name":"image","type":"rectanglelabels","origin":"manual"},{"original_width":2480,"original_height":3509,"image_rotation":0,"value":{"x":58.203125,"y":1.103448275862069,"width":37.6953125,"height":3.310344827586207,"rotation":0,"rectanglelabels":["company_info"]},"id":"eiVAVEgFA7","from_name":"label","to_name":"image","type":"rectanglelabels","origin":"manual"},{"original_width":2480,"original_height":3509,"image_rotation":0,"value":{"x":81.24999999999997,"y":6.482758620689654,"width":8.789062499999979,"height":1.9310344827586194,"rotation":0,"rectanglelabels":["account_number"]},"id":"0K_P0zDHYF","from_name":"label","to_name":"image","type":"rectanglelabels","origin":"manual"},{"original_width":2480,"original_height":3509,"image_rotation":0,"value":{"x":81.24999999999997,"y":8.413793103448278,"width":9.960937500000009,"height":1.9310344827586212,"rotation":0,"rectanglelabels":["invoice_date"]},"id":"cvhFfYYFQA","from_name":"label","to_name":"image","type":"rectanglelabels","origin":"manual"},{"original_width":2480,"original_height":3509,"image_rotation":0,"value":{"x":81.8359375,"y":10.344827586206897,"width":8.3984375,"height":1.6551724137931034,"rotation":0,"rectanglelabels":["page"]},"id":"eduAm_DPqF","from_name":"label","to_name":"image","type":"rectanglelabels","origin":"manual"},{"original_width":2480,"original_height":3509,"image_rotation":0,"value":{"x":68.5546875,"y":6.620689655172414,"width":12.5,"height":5.931034482758621,"rotation":0,"rectanglelabels":["other"]},"id":"iBlFhsw8Ia","from_name":"label","to_name":"image","type":"rectanglelabels","origin":"manual"},{"original_width":2480,"original_height":3509,"image_rotation":0,"value":{"x":10.546875,"y":15.586206896551724,"width":10.7421875,"height":7.724137931034483,"rotation":0,"rectanglelabels":["other"]},"id":"n3-qKTNSc9","from_name":"label","to_name":"image","type":"rectanglelabels","origin":"manual"},{"original_width":2480,"original_height":3509,"image_rotation":0,"value":{"x":21.6796875,"y":15.44827586206897,"width":13.8671875,"height":2.0689655172413803,"rotation":0,"rectanglelabels":["invoice_period"]},"id":"ATnWOKbFQ_","from_name":"label","to_name":"image","type":"rectanglelabels","origin":"manual"},{"original_width":2480,"original_height":3509,"image_rotation":0,"value":{"x":21.874999999999986,"y":17.793103448275847,"width":21.679687499999975,"height":1.5172413793103516,"rotation":0,"rectanglelabels":["product_name"]},"id":"5ou8a499OI","from_name":"label","to_name":"image","type":"rectanglelabels","origin":"manual"},{"original_width":2480,"original_height":3509,"image_rotation":0,"value":{"x":21.875,"y":19.724137931034484,"width":13.085937499999996,"height":1.3793103448275865,"rotation":0,"rectanglelabels":["charge_type"]},"id":"dfxl9B7ZC7","from_name":"label","to_name":"image","type":"rectanglelabels","origin":"manual"},{"original_width":2480,"original_height":3509,"image_rotation":0,"value":{"x":21.875,"y":21.379310344827587,"width":24.0234375,"height":4.9655172413793105,"rotation":0,"rectanglelabels":["site_address"]},"id":"EbQ3C8KyZJ","from_name":"label","to_name":"image","type":"rectanglelabels","origin":"manual"},{"original_width":2480,"original_height":3509,"image_rotation":0,"value":{"x":48.828125,"y":14.620689655172415,"width":47.4609375,"height":13.931034482758617,"rotation":0,"rectanglelabels":["other"]},"id":"JL-Bdqo0_d","from_name":"label","to_name":"image","type":"rectanglelabels","origin":"manual"},{"original_width":2480,"original_height":3509,"image_rotation":0,"value":{"x":4.1015625,"y":28.275862068965516,"width":92.3828125,"height":19.448275862068964,"rotation":0,"rectanglelabels":["other"]},"id":"GA6RPA7z1x","from_name":"label","to_name":"image","type":"rectanglelabels","origin":"manual"},{"original_width":2480,"original_height":3509,"image_rotation":0,"value":{"x":5.273437500000001,"y":49.79310344827583,"width":8.203124999999998,"height":2.4827586206896544,"rotation":0,"rectanglelabels":["other"]},"id":"vAswjuf0g4","from_name":"label","to_name":"image","type":"rectanglelabels","origin":"manual"},{"original_width":2480,"original_height":3509,"image_rotation":0,"value":{"x":85.93750000000003,"y":49.655172413793096,"width":9.179687500000005,"height":2.4827586206896637,"rotation":0,"rectanglelabels":["total_amount"]},"id":"aKUhEUbUo_","from_name":"label","to_name":"image","type":"rectanglelabels","origin":"manual"},{"original_width":2480,"original_height":3509,"image_rotation":0,"value":{"x":10.3515625,"y":93.37931034482759,"width":78.90625,"height":3.1724137931034484,"rotation":0,"rectanglelabels":["other"]},"id":"DtsVcOYMUS","from_name":"label","to_name":"image","type":"rectanglelabels","origin":"manual"}],"was_cancelled":false,"ground_truth":false,"created_at":"2023-12-18T07:40:35.184055Z","updated_at":"2023-12-18T15:48:54.308791Z","lead_time":288.639,"prediction":{},"result_count":0,"task":27,"parent_prediction":null,"parent_annotation":null}],"file_upload":"6a4ebe66-0016.jpg","drafts":[],"predictions":[],"data":{"image":"\/data\/upload\/4\/6a4ebe66-0016.jpg"},"meta":{},"created_at":"2023-12-18T04:15:16.433574Z","updated_at":"2023-12-18T15:48:54.329639Z","inner_id":10,"total_annotations":1,"cancelled_annotations":0,"total_predictions":0,"comment_count":0,"unresolved_comment_count":0,"last_comment_updated_at":null,"project":4,"updated_by":1,"comment_authors":[]},{"id":26,"annotations":[{"id":30,"completed_by":1,"result":[{"original_width":2480,"original_height":3509,"image_rotation":0,"value":{"x":5.2734375,"y":2.758620689655173,"width":37.6953125,"height":9.793103448275865,"rotation":0,"rectanglelabels":["other"]},"id":"skqLPmM7r2","from_name":"label","to_name":"image","type":"rectanglelabels","origin":"manual"},{"original_width":2480,"original_height":3509,"image_rotation":0,"value":{"x":58.59375,"y":1.103448275862069,"width":37.5,"height":4,"rotation":0,"rectanglelabels":["company_info"]},"id":"2XGF_TvUAx","from_name":"label","to_name":"image","type":"rectanglelabels","origin":"manual"},{"original_width":2480,"original_height":3509,"image_rotation":0,"value":{"x":81.25,"y":6.620689655172414,"width":9.375,"height":1.7931034482758617,"rotation":0,"rectanglelabels":["account_number"]},"id":"e_bD_0kpBn","from_name":"label","to_name":"image","type":"rectanglelabels","origin":"manual"},{"original_width":2480,"original_height":3509,"image_rotation":0,"value":{"x":80.859375,"y":8.275862068965518,"width":9.9609375,"height":1.7931034482758617,"rotation":0,"rectanglelabels":["invoice_date"]},"id":"cijc3_24Zw","from_name":"label","to_name":"image","type":"rectanglelabels","origin":"manual"},{"original_width":2480,"original_height":3509,"image_rotation":0,"value":{"x":81.25,"y":10.344827586206897,"width":9.1796875,"height":1.7931034482758617,"rotation":0,"rectanglelabels":["page"]},"id":"9XEqUa4iUJ","from_name":"label","to_name":"image","type":"rectanglelabels","origin":"manual"},{"original_width":2480,"original_height":3509,"image_rotation":0,"value":{"x":68.5546875,"y":6.482758620689655,"width":11.9140625,"height":6.068965517241379,"rotation":0,"rectanglelabels":["other"]},"id":"-AlomEnEga","from_name":"label","to_name":"image","type":"rectanglelabels","origin":"manual"},{"original_width":2480,"original_height":3509,"image_rotation":0,"value":{"x":9.5703125,"y":15.172413793103448,"width":11.9140625,"height":7.310344827586207,"rotation":0,"rectanglelabels":["other"]},"id":"4LKXhhm1Zw","from_name":"label","to_name":"image","type":"rectanglelabels","origin":"manual"},{"original_width":2480,"original_height":3509,"image_rotation":0,"value":{"x":22.0703125,"y":15.310344827586206,"width":13.0859375,"height":2.206896551724138,"rotation":0,"rectanglelabels":["invoice_period"]},"id":"zg6r3sXQz9","from_name":"label","to_name":"image","type":"rectanglelabels","origin":"manual"},{"original_width":2480,"original_height":3509,"image_rotation":0,"value":{"x":22.070312499999993,"y":17.517241379310345,"width":21.289062499999968,"height":1.6551724137931034,"rotation":0,"rectanglelabels":["product_name"]},"id":"HE1xsVLT4_","from_name":"label","to_name":"image","type":"rectanglelabels","origin":"manual"},{"original_width":2480,"original_height":3509,"image_rotation":0,"value":{"x":22.0703125,"y":19.58620689655173,"width":25,"height":5.793103448275862,"rotation":0,"rectanglelabels":["site_address"]},"id":"X5QSvi9Mgv","from_name":"label","to_name":"image","type":"rectanglelabels","origin":"manual"},{"original_width":2480,"original_height":3509,"image_rotation":0,"value":{"x":3.90625,"y":27.448275862068964,"width":92.578125,"height":32.13793103448276,"rotation":0,"rectanglelabels":["other"]},"id":"klUHyQim8g","from_name":"label","to_name":"image","type":"rectanglelabels","origin":"manual"},{"original_width":2480,"original_height":3509,"image_rotation":0,"value":{"x":5.273437499999999,"y":62.20689655172415,"width":8.593749999999998,"height":2.482758620689639,"rotation":0,"rectanglelabels":["other"]},"id":"UEuEba9Wn-","from_name":"label","to_name":"image","type":"rectanglelabels","origin":"manual"},{"original_width":2480,"original_height":3509,"image_rotation":0,"value":{"x":86.1328125,"y":62.206896551724135,"width":8.7890625,"height":2.3448275862068972,"rotation":0,"rectanglelabels":["total_amount"]},"id":"cXfGH2V2nY","from_name":"label","to_name":"image","type":"rectanglelabels","origin":"manual"},{"original_width":2480,"original_height":3509,"image_rotation":0,"value":{"x":10.546875,"y":93.65517241379311,"width":79.1015625,"height":2.6206896551724137,"rotation":0,"rectanglelabels":["other"]},"id":"Pjae8ulKkz","from_name":"label","to_name":"image","type":"rectanglelabels","origin":"manual"}],"was_cancelled":false,"ground_truth":false,"created_at":"2023-12-18T07:35:54.524616Z","updated_at":"2023-12-18T15:48:43.431773Z","lead_time":246.81900000000002,"prediction":{},"result_count":0,"task":26,"parent_prediction":null,"parent_annotation":null}],"file_upload":"25177346-0015.jpg","drafts":[],"predictions":[],"data":{"image":"\/data\/upload\/4\/25177346-0015.jpg"},"meta":{},"created_at":"2023-12-18T04:15:16.433574Z","updated_at":"2023-12-18T15:48:43.454412Z","inner_id":9,"total_annotations":1,"cancelled_annotations":0,"total_predictions":0,"comment_count":0,"unresolved_comment_count":0,"last_comment_updated_at":null,"project":4,"updated_by":1,"comment_authors":[]},{"id":25,"annotations":[{"id":29,"completed_by":1,"result":[{"original_width":2480,"original_height":3509,"image_rotation":0,"value":{"x":5.46875,"y":3.5862068965517233,"width":37.6953125,"height":9.517241379310342,"rotation":0,"rectanglelabels":["other"]},"id":"CUtjFUYDCG","from_name":"label","to_name":"image","type":"rectanglelabels","origin":"manual"},{"original_width":2480,"original_height":3509,"image_rotation":0,"value":{"x":58.203125,"y":0.8275862068965517,"width":37.6953125,"height":4.137931034482759,"rotation":0,"rectanglelabels":["company_info"]},"id":"TS4Mboy0Lt","from_name":"label","to_name":"image","type":"rectanglelabels","origin":"manual"},{"original_width":2480,"original_height":3509,"image_rotation":0,"value":{"x":68.1640625,"y":6.344827586206897,"width":12.5,"height":6.482758620689655,"rotation":0,"rectanglelabels":["other"]},"id":"0QQzjLSjP1","from_name":"label","to_name":"image","type":"rectanglelabels","origin":"manual"},{"original_width":2480,"original_height":3509,"image_rotation":0,"value":{"x":81.25,"y":6.620689655172414,"width":8.59375,"height":1.7931034482758617,"rotation":0,"rectanglelabels":["account_number"]},"id":"SAu2gLdI5u","from_name":"label","to_name":"image","type":"rectanglelabels","origin":"manual"},{"original_width":2480,"original_height":3509,"image_rotation":0,"value":{"x":81.25,"y":8.551724137931034,"width":9.9609375,"height":1.6551724137931034,"rotation":0,"rectanglelabels":["invoice_date"]},"id":"8hiijOE925","from_name":"label","to_name":"image","type":"rectanglelabels","origin":"manual"},{"original_width":2480,"original_height":3509,"image_rotation":0,"value":{"x":82.2265625,"y":10.20689655172414,"width":8.0078125,"height":1.7931034482758617,"rotation":0,"rectanglelabels":["page"]},"id":"_vcvTYznK4","from_name":"label","to_name":"image","type":"rectanglelabels","origin":"manual"},{"original_width":2480,"original_height":3509,"image_rotation":0,"value":{"x":10.546875,"y":15.724137931034482,"width":10.7421875,"height":7.448275862068964,"rotation":0,"rectanglelabels":["other"]},"id":"ijbxPl-Fvk","from_name":"label","to_name":"image","type":"rectanglelabels","origin":"manual"},{"original_width":2480,"original_height":3509,"image_rotation":0,"value":{"x":22.0703125,"y":15.586206896551724,"width":13.0859375,"height":1.6551724137931034,"rotation":0,"rectanglelabels":["invoice_period"]},"id":"fxK5yeYmQQ","from_name":"label","to_name":"image","type":"rectanglelabels","origin":"manual"},{"original_width":2480,"original_height":3509,"image_rotation":0,"value":{"x":22.0703125,"y":17.517241379310345,"width":21.09375,"height":1.7931034482758617,"rotation":0,"rectanglelabels":["product_name"]},"id":"j1C_-VWEML","from_name":"label","to_name":"image","type":"rectanglelabels","origin":"manual"},{"original_width":2480,"original_height":3509,"image_rotation":0,"value":{"x":22.070312499999996,"y":19.58620689655173,"width":11.914062499999996,"height":1.6551724137931034,"rotation":0,"rectanglelabels":["charge_type"]},"id":"3N1MMFPuPa","from_name":"label","to_name":"image","type":"rectanglelabels","origin":"manual"},{"original_width":2480,"original_height":3509,"image_rotation":0,"value":{"x":21.875000000000004,"y":21.517241379310345,"width":13.671875000000005,"height":4.827586206896551,"rotation":0,"rectanglelabels":["site_address"]},"id":"N40DAY4-PD","from_name":"label","to_name":"image","type":"rectanglelabels","origin":"manual"},{"original_width":2480,"original_height":3509,"image_rotation":0,"value":{"x":49.023437500000014,"y":15.034482758620685,"width":46.67968750000001,"height":13.517241379310345,"rotation":0,"rectanglelabels":["other"]},"id":"_HqEbCn60b","from_name":"label","to_name":"image","type":"rectanglelabels","origin":"manual"},{"original_width":2480,"original_height":3509,"image_rotation":0,"value":{"x":3.515625,"y":28.689655172413786,"width":92.7734375,"height":19.310344827586235,"rotation":0,"rectanglelabels":["other"]},"id":"7DhMND11WT","from_name":"label","to_name":"image","type":"rectanglelabels","origin":"manual"},{"original_width":2480,"original_height":3509,"image_rotation":0,"value":{"x":84.375,"y":49.6551724137931,"width":10.3515625,"height":2.6206896551724137,"rotation":0,"rectanglelabels":["total_amount"]},"id":"gm_-SucBVk","from_name":"label","to_name":"image","type":"rectanglelabels","origin":"manual"},{"original_width":2480,"original_height":3509,"image_rotation":0,"value":{"x":4.8828125,"y":49.6551724137931,"width":9.1796875,"height":2.4827586206896552,"rotation":0,"rectanglelabels":["other"]},"id":"z9lrYTPTDZ","from_name":"label","to_name":"image","type":"rectanglelabels","origin":"manual"},{"original_width":2480,"original_height":3509,"image_rotation":0,"value":{"x":10.7421875,"y":93.51724137931035,"width":78.90625,"height":2.758620689655173,"rotation":0,"rectanglelabels":["other"]},"id":"EOwKQetSwX","from_name":"label","to_name":"image","type":"rectanglelabels","origin":"manual"}],"was_cancelled":false,"ground_truth":false,"created_at":"2023-12-18T07:29:32.587932Z","updated_at":"2023-12-18T15:48:29.789521Z","lead_time":250.55199999999996,"prediction":{},"result_count":0,"task":25,"parent_prediction":null,"parent_annotation":null}],"file_upload":"7458c956-0014.jpg","drafts":[],"predictions":[],"data":{"image":"\/data\/upload\/4\/7458c956-0014.jpg"},"meta":{},"created_at":"2023-12-18T04:15:16.433574Z","updated_at":"2023-12-18T15:48:29.811197Z","inner_id":8,"total_annotations":1,"cancelled_annotations":0,"total_predictions":0,"comment_count":0,"unresolved_comment_count":0,"last_comment_updated_at":null,"project":4,"updated_by":1,"comment_authors":[]},{"id":24,"annotations":[{"id":28,"completed_by":1,"result":[{"original_width":2480,"original_height":3509,"image_rotation":0,"value":{"x":5.6640625,"y":3.034482758620689,"width":37.304687499999986,"height":9.655172413793101,"rotation":0,"rectanglelabels":["other"]},"id":"m17BgjCYPE","from_name":"label","to_name":"image","type":"rectanglelabels","origin":"manual"},{"original_width":2480,"original_height":3509,"image_rotation":0,"value":{"x":58.0078125,"y":0.8275862068965517,"width":38.0859375,"height":3.8620689655172415,"rotation":0,"rectanglelabels":["company_info"]},"id":"Qrk79-jRfq","from_name":"label","to_name":"image","type":"rectanglelabels","origin":"manual"},{"original_width":2480,"original_height":3509,"image_rotation":0,"value":{"x":80.90897351615327,"y":6.620689655172411,"width":9.13008898384675,"height":1.6551724137931034,"rotation":0,"rectanglelabels":["account_number"]},"id":"0gCmH2xYm8","from_name":"label","to_name":"image","type":"rectanglelabels","origin":"manual"},{"original_width":2480,"original_height":3509,"image_rotation":0,"value":{"x":81.31632700976706,"y":8.426332288401253,"width":10.054411626596519,"height":1.6551724137931028,"rotation":0,"rectanglelabels":["invoice_date"]},"id":"K5-4BLx-Lq","from_name":"label","to_name":"image","type":"rectanglelabels","origin":"manual"},{"original_width":2480,"original_height":3509,"image_rotation":0,"value":{"x":81.49857954545455,"y":10.062695924764895,"width":8.52272727272727,"height":2.0062695924764893,"rotation":0,"rectanglelabels":["page"]},"id":"e2mUaYokGz","from_name":"label","to_name":"image","type":"rectanglelabels","origin":"manual"},{"original_width":2480,"original_height":3509,"image_rotation":0,"value":{"x":67.77343750000001,"y":6.620689655172414,"width":12.6953125,"height":5.793103448275865,"rotation":0,"rectanglelabels":["other"]},"id":"gV-uuqsZaf","from_name":"label","to_name":"image","type":"rectanglelabels","origin":"manual"},{"original_width":2480,"original_height":3509,"image_rotation":0,"value":{"x":9.5703125,"y":15.586206896551724,"width":11.71875,"height":5.793103448275862,"rotation":0,"rectanglelabels":["other"]},"id":"xuXIQ8nidO","from_name":"label","to_name":"image","type":"rectanglelabels","origin":"manual"},{"original_width":2480,"original_height":3509,"image_rotation":0,"value":{"x":21.875000000000004,"y":15.586206896551722,"width":13.28125000000001,"height":1.7931034482758617,"rotation":0,"rectanglelabels":["invoice_period"]},"id":"N4uB4AKgur","from_name":"label","to_name":"image","type":"rectanglelabels","origin":"manual"},{"original_width":2480,"original_height":3509,"image_rotation":0,"value":{"x":21.875,"y":17.379310344827587,"width":21.6796875,"height":1.6551724137931034,"rotation":0,"rectanglelabels":["product_name"]},"id":"_fG8GhPIQ3","from_name":"label","to_name":"image","type":"rectanglelabels","origin":"manual"},{"original_width":2480,"original_height":3509,"image_rotation":0,"value":{"x":21.679687499999993,"y":19.724137931034477,"width":14.84375,"height":4.6896551724137865,"rotation":0,"rectanglelabels":["other"]},"id":"ffpy5tJz0w","from_name":"label","to_name":"image","type":"rectanglelabels","origin":"manual"},{"original_width":2480,"original_height":3509,"image_rotation":0,"value":{"x":3.90625,"y":26.758620689655167,"width":92.57812499999997,"height":33.65517241379309,"rotation":0,"rectanglelabels":["other"]},"id":"1l3mPAAeTu","from_name":"label","to_name":"image","type":"rectanglelabels","origin":"manual"},{"original_width":2480,"original_height":3509,"image_rotation":0,"value":{"x":84.1796875,"y":62.06896551724138,"width":10.7421875,"height":2.4827586206896552,"rotation":0,"rectanglelabels":["total_amount"]},"id":"1Yz4Rem-VN","from_name":"label","to_name":"image","type":"rectanglelabels","origin":"manual"},{"original_width":2480,"original_height":3509,"image_rotation":0,"value":{"x":4.8828125,"y":62.06896551724138,"width":9.5703125,"height":2.758620689655173,"rotation":0,"rectanglelabels":["other"]},"id":"uzyk9PqBrV","from_name":"label","to_name":"image","type":"rectanglelabels","origin":"manual"},{"original_width":2480,"original_height":3509,"image_rotation":0,"value":{"x":10.3515625,"y":93.51724137931035,"width":79.1015625,"height":2.758620689655173,"rotation":0,"rectanglelabels":["other"]},"id":"oaCuG-bVaI","from_name":"label","to_name":"image","type":"rectanglelabels","origin":"manual"}],"was_cancelled":false,"ground_truth":false,"created_at":"2023-12-18T07:25:53.870603Z","updated_at":"2023-12-18T15:48:16.414579Z","lead_time":253.51199999999997,"prediction":{},"result_count":0,"task":24,"parent_prediction":null,"parent_annotation":null}],"file_upload":"860f329f-0013.jpg","drafts":[],"predictions":[],"data":{"image":"\/data\/upload\/4\/860f329f-0013.jpg"},"meta":{},"created_at":"2023-12-18T04:15:16.433574Z","updated_at":"2023-12-18T15:48:16.437253Z","inner_id":7,"total_annotations":1,"cancelled_annotations":0,"total_predictions":0,"comment_count":0,"unresolved_comment_count":0,"last_comment_updated_at":null,"project":4,"updated_by":1,"comment_authors":[]},{"id":23,"annotations":[{"id":27,"completed_by":1,"result":[{"original_width":2480,"original_height":3509,"image_rotation":0,"value":{"x":57.8125,"y":0.27586206896551724,"width":38.28125,"height":4.413793103448276,"rotation":0,"rectanglelabels":["company_info"]},"id":"7q0xbsAcAK","from_name":"label","to_name":"image","type":"rectanglelabels","origin":"manual"},{"original_width":2480,"original_height":3509,"image_rotation":0,"value":{"x":81.0546875,"y":6.482758620689655,"width":8.984375,"height":1.793103448275862,"rotation":0,"rectanglelabels":["account_number"]},"id":"D_9mWFrL-9","from_name":"label","to_name":"image","type":"rectanglelabels","origin":"manual"},{"original_width":2480,"original_height":3509,"image_rotation":0,"value":{"x":81.3177944214876,"y":8.713593616414935,"width":9.502518078512354,"height":1.3553719008264458,"rotation":0,"rectanglelabels":["invoice_date"]},"id":"qPdorcOOWv","from_name":"label","to_name":"image","type":"rectanglelabels","origin":"manual"},{"original_width":2480,"original_height":3509,"image_rotation":0,"value":{"x":82.13294163223142,"y":10.482758620689655,"width":7.320183367768564,"height":1.3793103448275854,"rotation":0,"rectanglelabels":["page"]},"id":"0_OzZkoGY3","from_name":"label","to_name":"image","type":"rectanglelabels","origin":"manual"},{"original_width":2480,"original_height":3509,"image_rotation":0,"value":{"x":3.3203125,"y":2.758620689655173,"width":40.4296875,"height":10.20689655172414,"rotation":0,"rectanglelabels":["other"]},"id":"8dIrpoRE7r","from_name":"label","to_name":"image","type":"rectanglelabels","origin":"manual"},{"original_width":2480,"original_height":3509,"image_rotation":0,"value":{"x":67.96875,"y":6.344827586206897,"width":12.5,"height":6.068965517241379,"rotation":0,"rectanglelabels":["other"]},"id":"JnZK0a_gLR","from_name":"label","to_name":"image","type":"rectanglelabels","origin":"manual"},{"original_width":2480,"original_height":3509,"image_rotation":0,"value":{"x":9.765625,"y":15.586206896551724,"width":11.5234375,"height":8.137931034482758,"rotation":0,"rectanglelabels":["other"]},"id":"4eTqlOknvB","from_name":"label","to_name":"image","type":"rectanglelabels","origin":"manual"},{"original_width":2480,"original_height":3509,"image_rotation":0,"value":{"x":22.07031250000001,"y":15.586206896551722,"width":12.890624999999996,"height":1.7931034482758637,"rotation":0,"rectanglelabels":["invoice_period"]},"id":"CGd52K_Vu5","from_name":"label","to_name":"image","type":"rectanglelabels","origin":"manual"},{"original_width":2480,"original_height":3509,"image_rotation":0,"value":{"x":21.57095229151014,"y":17.71937096815981,"width":21.570952291510096,"height":1.76170367107956,"rotation":0,"rectanglelabels":["product_name"]},"id":"c2rkc1iBuE","from_name":"label","to_name":"image","type":"rectanglelabels","origin":"manual"},{"original_width":2480,"original_height":3509,"image_rotation":0,"value":{"x":22.011175807663406,"y":19.48107463923937,"width":12.619740796393684,"height":1.6580740433689973,"rotation":0,"rectanglelabels":["charge_type"]},"id":"kZOBsegjiR","from_name":"label","to_name":"image","type":"rectanglelabels","origin":"manual"},{"original_width":2480,"original_height":3509,"image_rotation":0,"value":{"x":22.011175807663406,"y":21.24277831031893,"width":13.059964312546954,"height":5.285111013238686,"rotation":0,"rectanglelabels":["site_address"]},"id":"qWcaJiq6hd","from_name":"label","to_name":"image","type":"rectanglelabels","origin":"manual"},{"original_width":2480,"original_height":3509,"image_rotation":0,"value":{"x":83.64246806912095,"y":50.05181481385528,"width":11.299070247933884,"height":2.0725925542112718,"rotation":0,"rectanglelabels":["total_amount"]},"id":"ZSAJHky765","from_name":"label","to_name":"image","type":"rectanglelabels","origin":"manual"},{"original_width":2480,"original_height":3509,"image_rotation":0,"value":{"x":49.15829263711494,"y":15.025000647685186,"width":46.37021036814424,"height":14.093629368636492,"rotation":0,"rectanglelabels":["other"]},"id":"2xgPJz4SlY","from_name":"label","to_name":"image","type":"rectanglelabels","origin":"manual"},{"original_width":2480,"original_height":3509,"image_rotation":0,"value":{"x":5.429423365890305,"y":49.844555558434145,"width":8.217505634861002,"height":2.2798518096323726,"rotation":0,"rectanglelabels":["other"]},"id":"3STCwPkVIa","from_name":"label","to_name":"image","type":"rectanglelabels","origin":"manual"},{"original_width":2480,"original_height":3509,"image_rotation":0,"value":{"x":3.8152704733283236,"y":29.016295758957476,"width":92.00671487603304,"height":18.7569626156118,"rotation":0,"rectanglelabels":["other"]},"id":"GDhM76X9RR","from_name":"label","to_name":"image","type":"rectanglelabels","origin":"manual"},{"original_width":2480,"original_height":3509,"image_rotation":0,"value":{"x":10.15625,"y":93.65517241379311,"width":79.4921875,"height":2.6206896551724137,"rotation":0,"rectanglelabels":["other"]},"id":"WKxhw_pB26","from_name":"label","to_name":"image","type":"rectanglelabels","origin":"manual"}],"was_cancelled":false,"ground_truth":false,"created_at":"2023-12-18T07:14:27.557542Z","updated_at":"2023-12-18T15:48:01.774468Z","lead_time":491.35100000000006,"prediction":{},"result_count":0,"task":23,"parent_prediction":null,"parent_annotation":null}],"file_upload":"34ee859d-0012.jpg","drafts":[],"predictions":[],"data":{"image":"\/data\/upload\/4\/34ee859d-0012.jpg"},"meta":{},"created_at":"2023-12-18T04:15:16.433574Z","updated_at":"2023-12-18T15:48:01.799467Z","inner_id":6,"total_annotations":1,"cancelled_annotations":0,"total_predictions":0,"comment_count":0,"unresolved_comment_count":0,"last_comment_updated_at":null,"project":4,"updated_by":1,"comment_authors":[]},{"id":22,"annotations":[{"id":26,"completed_by":1,"result":[{"original_width":2480,"original_height":3509,"image_rotation":0,"value":{"x":4.882812499999999,"y":3.034482758620689,"width":38.47656250000001,"height":10.344827586206893,"rotation":0,"rectanglelabels":["other"]},"id":"cWg6Z0thjQ","from_name":"label","to_name":"image","type":"rectanglelabels","origin":"manual"},{"original_width":2480,"original_height":3509,"image_rotation":0,"value":{"x":57.6171875,"y":0.27586206896551724,"width":38.4765625,"height":4.6896551724137945,"rotation":0,"rectanglelabels":["company_info"]},"id":"tRKocK9e_q","from_name":"label","to_name":"image","type":"rectanglelabels","origin":"manual"},{"original_width":2480,"original_height":3509,"image_rotation":0,"value":{"x":67.77343749999997,"y":5.517241379310346,"width":13.08593750000002,"height":7.310344827586207,"rotation":0,"rectanglelabels":["other"]},"id":"8Y87tTtFLa","from_name":"label","to_name":"image","type":"rectanglelabels","origin":"manual"},{"original_width":2480,"original_height":3509,"image_rotation":0,"value":{"x":81.44531250000003,"y":6.206896551724138,"width":8.398437499999998,"height":2.0689655172413794,"rotation":0,"rectanglelabels":["account_number"]},"id":"y3AqXyyiW7","from_name":"label","to_name":"image","type":"rectanglelabels","origin":"manual"},{"original_width":2480,"original_height":3509,"image_rotation":0,"value":{"x":81.32102272727273,"y":8.432601880877744,"width":10.004813110443303,"height":1.6300940438871472,"rotation":0,"rectanglelabels":["invoice_date"]},"id":"xntXtP3XV7","from_name":"label","to_name":"image","type":"rectanglelabels","origin":"manual"},{"original_width":2480,"original_height":3509,"image_rotation":0,"value":{"x":82.20880681818183,"y":10.43887147335424,"width":7.102272727272729,"height":1.880877742946708,"rotation":0,"rectanglelabels":["page"]},"id":"13QHy-30Ds","from_name":"label","to_name":"image","type":"rectanglelabels","origin":"manual"},{"original_width":2480,"original_height":3509,"image_rotation":0,"value":{"x":10.271882043576255,"y":15.958962667426613,"width":11.152329075882792,"height":5.388740640949246,"rotation":0,"rectanglelabels":["other"]},"id":"lAghp9BQrb","from_name":"label","to_name":"image","type":"rectanglelabels","origin":"manual"},{"original_width":2480,"original_height":3509,"image_rotation":0,"value":{"x":22.011175807663406,"y":15.751703412005488,"width":13.64692900075131,"height":1.6580740433689993,"rotation":0,"rectanglelabels":["invoice_period"]},"id":"j0fSZ8Yvgj","from_name":"label","to_name":"image","type":"rectanglelabels","origin":"manual"},{"original_width":2480,"original_height":3509,"image_rotation":0,"value":{"x":22.104209710743806,"y":17.51724137931033,"width":21.60382231404959,"height":1.655172413793105,"rotation":0,"rectanglelabels":["product_name"]},"id":"0-PsYpwJdX","from_name":"label","to_name":"image","type":"rectanglelabels","origin":"manual"},{"original_width":2480,"original_height":3509,"image_rotation":0,"value":{"x":22.11389462809917,"y":19.620974636648622,"width":12.91322314049587,"height":4.901681390709604,"rotation":0,"rectanglelabels":["site_address"]},"id":"F27MspIihK","from_name":"label","to_name":"image","type":"rectanglelabels","origin":"manual"},{"original_width":2480,"original_height":3509,"image_rotation":0,"value":{"x":3.5511363636363624,"y":26.57452265602734,"width":93.94369834710743,"height":33.28583642063268,"rotation":0,"rectanglelabels":["other"]},"id":"9iaMrPmEt_","from_name":"label","to_name":"image","type":"rectanglelabels","origin":"manual"},{"original_width":2480,"original_height":3509,"image_rotation":0,"value":{"x":83.93595041322313,"y":62.140210886292394,"width":11.46048553719009,"height":2.393844400113988,"rotation":0,"rectanglelabels":["total_amount"]},"id":"ucmjLah8-2","from_name":"label","to_name":"image","type":"rectanglelabels","origin":"manual"},{"original_width":2480,"original_height":3509,"image_rotation":0,"value":{"x":5.649535123966942,"y":62.36819606725563,"width":7.909349173553718,"height":2.051866628669139,"rotation":0,"rectanglelabels":["other"]},"id":"Wm2l1Ip-LB","from_name":"label","to_name":"image","type":"rectanglelabels","origin":"manual"},{"original_width":2480,"original_height":3509,"image_rotation":0,"value":{"x":10.351562499999996,"y":93.79310344827584,"width":79.29687499999997,"height":2.482758620689639,"rotation":0,"rectanglelabels":["other"]},"id":"vE5-NbPgig","from_name":"label","to_name":"image","type":"rectanglelabels","origin":"manual"}],"was_cancelled":false,"ground_truth":false,"created_at":"2023-12-18T07:07:22.625632Z","updated_at":"2023-12-18T15:47:31.807459Z","lead_time":140.30700000000002,"prediction":{},"result_count":0,"task":22,"parent_prediction":null,"parent_annotation":null}],"file_upload":"439bf0c3-0011.jpg","drafts":[],"predictions":[],"data":{"image":"\/data\/upload\/4\/439bf0c3-0011.jpg"},"meta":{},"created_at":"2023-12-18T04:15:16.433574Z","updated_at":"2023-12-18T15:47:31.832460Z","inner_id":5,"total_annotations":1,"cancelled_annotations":0,"total_predictions":0,"comment_count":0,"unresolved_comment_count":0,"last_comment_updated_at":null,"project":4,"updated_by":1,"comment_authors":[]},{"id":20,"annotations":[{"id":24,"completed_by":1,"result":[{"original_width":2480,"original_height":3509,"image_rotation":0,"value":{"x":58.203125,"y":1.103448275862069,"width":37.5,"height":3.310344827586207,"rotation":0,"rectanglelabels":["company_info"]},"id":"XtMw1kCdG8","from_name":"label","to_name":"image","type":"rectanglelabels","origin":"manual"},{"original_width":2480,"original_height":3509,"image_rotation":0,"value":{"x":4.8828125,"y":2.6206896551724137,"width":38.0859375,"height":10.20689655172414,"rotation":0,"rectanglelabels":["other"]},"id":"S4_vlMyEcl","from_name":"label","to_name":"image","type":"rectanglelabels","origin":"manual"},{"original_width":2480,"original_height":3509,"image_rotation":0,"value":{"x":81.0546875,"y":6.620689655172414,"width":9.1796875,"height":1.6551724137931034,"rotation":0,"rectanglelabels":["account_number"]},"id":"Y40XuOGAXr","from_name":"label","to_name":"image","type":"rectanglelabels","origin":"manual"},{"original_width":2480,"original_height":3509,"image_rotation":0,"value":{"x":81.05468749999997,"y":8.72395657918599,"width":10.156250000000004,"height":1.3450089380553871,"rotation":0,"rectanglelabels":["invoice_date"]},"id":"mg7Z2ZQ3nq","from_name":"label","to_name":"image","type":"rectanglelabels","origin":"manual"},{"original_width":2480,"original_height":3509,"image_rotation":0,"value":{"x":82.32179752066114,"y":10.466592398766805,"width":6.603352742299018,"height":1.4508147879478732,"rotation":0,"rectanglelabels":["page"]},"id":"25hXeLfwVE","from_name":"label","to_name":"image","type":"rectanglelabels","origin":"manual"},{"original_width":2480,"original_height":3509,"image_rotation":0,"value":{"x":68.52812734785871,"y":6.217777662633746,"width":12.032776108189344,"height":6.010518407212618,"rotation":0,"rectanglelabels":["other"]},"id":"ds3M9kEPZz","from_name":"label","to_name":"image","type":"rectanglelabels","origin":"manual"},{"original_width":2480,"original_height":3509,"image_rotation":0,"value":{"x":21.86443463561232,"y":15.544444156584364,"width":13.646929000751307,"height":1.8653332987901232,"rotation":0,"rectanglelabels":["invoice_period"]},"id":"VzVTxOCJLy","from_name":"label","to_name":"image","type":"rectanglelabels","origin":"manual"},{"original_width":2480,"original_height":3509,"image_rotation":0,"value":{"x":21.57095229151014,"y":17.738651645794782,"width":21.71769346356122,"height":1.536459108369832,"rotation":0,"rectanglelabels":["product_name"]},"id":"QRZgd68_22","from_name":"label","to_name":"image","type":"rectanglelabels","origin":"manual"},{"original_width":2480,"original_height":3509,"image_rotation":0,"value":{"x":21.952479338842974,"y":19.506982046167007,"width":11.78331611570248,"height":5.243659162154456,"rotation":0,"rectanglelabels":["site_address"]},"id":"Miw9_TaoNa","from_name":"label","to_name":"image","type":"rectanglelabels","origin":"manual"},{"original_width":2480,"original_height":3509,"image_rotation":0,"value":{"x":10.330578512396693,"y":15.631233969791971,"width":10.976239669421487,"height":5.813622114562554,"rotation":0,"rectanglelabels":["other"]},"id":"H8iIscfnS3","from_name":"label","to_name":"image","type":"rectanglelabels","origin":"manual"},{"original_width":2480,"original_height":3509,"image_rotation":0,"value":{"x":85.71151859504131,"y":62.36819606725563,"width":9.0392561983471,"height":2.051866628669139,"rotation":0,"rectanglelabels":["total_amount"]},"id":"4HTv3AWiyQ","from_name":"label","to_name":"image","type":"rectanglelabels","origin":"manual"},{"original_width":2480,"original_height":3509,"image_rotation":0,"value":{"x":3.5511363636363633,"y":26.346537475064125,"width":93.62086776859503,"height":33.969791963522376,"rotation":0,"rectanglelabels":["other"]},"id":"ScFjjXFxrc","from_name":"label","to_name":"image","type":"rectanglelabels","origin":"manual"},{"original_width":2480,"original_height":3509,"image_rotation":0,"value":{"x":5.078125,"y":61.93103448275862,"width":8.7890625,"height":2.6206896551724137,"rotation":0,"rectanglelabels":["other"]},"id":"DW-9jKCVOJ","from_name":"label","to_name":"image","type":"rectanglelabels","origin":"manual"},{"original_width":2480,"original_height":3509,"image_rotation":0,"value":{"x":10.156249999999993,"y":93.51724137931035,"width":78.90624999999994,"height":2.7586206896551717,"rotation":0,"rectanglelabels":["other"]},"id":"gIoo9mbxr2","from_name":"label","to_name":"image","type":"rectanglelabels","origin":"manual"}],"was_cancelled":false,"ground_truth":false,"created_at":"2023-12-18T04:44:35.582539Z","updated_at":"2023-12-18T15:46:58.407295Z","lead_time":8402.833,"prediction":{},"result_count":0,"task":20,"parent_prediction":null,"parent_annotation":null}],"file_upload":"0952d433-0009.jpg","drafts":[],"predictions":[],"data":{"image":"\/data\/upload\/4\/0952d433-0009.jpg"},"meta":{},"created_at":"2023-12-18T04:15:16.433574Z","updated_at":"2023-12-18T15:46:58.431886Z","inner_id":3,"total_annotations":1,"cancelled_annotations":0,"total_predictions":0,"comment_count":0,"unresolved_comment_count":0,"last_comment_updated_at":null,"project":4,"updated_by":1,"comment_authors":[]},{"id":19,"annotations":[{"id":23,"completed_by":1,"result":[{"original_width":3509,"original_height":2480,"image_rotation":0,"value":{"x":3.1679659339752795,"y":4.840252833295774,"width":27.37122566954642,"height":10.756117407323943,"rotation":0,"rectanglelabels":["other"]},"id":"YUTXiKKOj6","from_name":"label","to_name":"image","type":"rectanglelabels","origin":"manual"},{"original_width":3509,"original_height":2480,"image_rotation":0,"value":{"x":10.264209626079907,"y":17.389056475173707,"width":8.490148703053748,"height":2.330492104920189,"rotation":0,"rectanglelabels":["invoice_period"]},"id":"X_YihqdUc3","from_name":"label","to_name":"image","type":"rectanglelabels","origin":"manual"},{"original_width":3509,"original_height":2480,"image_rotation":0,"value":{"x":3.1679659339752697,"y":17.56832509862907,"width":6.842806417386586,"height":2.151223481464805,"rotation":0,"rectanglelabels":["other"]},"id":"reHG6Jq69Z","from_name":"label","to_name":"image","type":"rectanglelabels","origin":"manual"},{"original_width":3509,"original_height":2480,"image_rotation":0,"value":{"x":70.85471340742741,"y":2.1512234814647866,"width":26.230757933315278,"height":4.302446962929573,"rotation":0,"rectanglelabels":["company_info"]},"id":"31zMZKJ2G4","from_name":"label","to_name":"image","type":"rectanglelabels","origin":"manual"},{"original_width":3509,"original_height":2480,"image_rotation":0,"value":{"x":86.56782443994477,"y":9.680505666591545,"width":6.335931867950497,"height":2.330492104920186,"rotation":0,"rectanglelabels":["account_number"]},"id":"6vN6eI7eM9","from_name":"label","to_name":"image","type":"rectanglelabels","origin":"manual"},{"original_width":3509,"original_height":2480,"image_rotation":0,"value":{"x":77.44408255009564,"y":9.68050566659147,"width":8.616867340413032,"height":8.067088055493006,"rotation":0,"rectanglelabels":["other"]},"id":"tGHhOWZN0r","from_name":"label","to_name":"image","type":"rectanglelabels","origin":"manual"},{"original_width":3509,"original_height":2480,"image_rotation":0,"value":{"x":86.61180942150737,"y":12.634734056426794,"width":6.798821435823934,"height":2.244561690371308,"rotation":0,"rectanglelabels":["invoice_date"]},"id":"8mNnqYKTrd","from_name":"label","to_name":"image","type":"rectanglelabels","origin":"manual"},{"original_width":3509,"original_height":2480,"image_rotation":0,"value":{"x":87.16109806030742,"y":15.26079715621767,"width":4.6079504494185946,"height":1.9260265329918906,"rotation":0,"rectanglelabels":["page"]},"id":"b4kRCi_Xy3","from_name":"label","to_name":"image","type":"rectanglelabels","origin":"manual"},{"original_width":3509,"original_height":2480,"image_rotation":0,"value":{"x":3.0735455543358947,"y":22.82608695652174,"width":94.07244785949506,"height":26.08695652173913,"rotation":0,"rectanglelabels":["other"]},"id":"nCabHRQRpw","from_name":"label","to_name":"image","type":"rectanglelabels","origin":"manual"},{"original_width":3509,"original_height":2480,"image_rotation":0,"value":{"x":3.841931942919868,"y":53.41614906832298,"width":13.391877058177833,"height":3.1055900621118013,"rotation":0,"rectanglelabels":["other"]},"id":"xk1Wjd6Nud","from_name":"label","to_name":"image","type":"rectanglelabels","origin":"manual"},{"original_width":3509,"original_height":2480,"image_rotation":0,"value":{"x":48.40834248079034,"y":53.10559006211179,"width":3.7321624588364433,"height":3.4161490683229814,"rotation":0,"rectanglelabels":["total_units"]},"id":"BKAXV_2PbW","from_name":"label","to_name":"image","type":"rectanglelabels","origin":"manual"},{"original_width":3509,"original_height":2480,"image_rotation":0,"value":{"x":55.937531184512515,"y":53.811405985319034,"width":6.286797724777952,"height":2.2586109542631307,"rotation":0,"rectanglelabels":["total_consumption_charges"]},"id":"riypYxTDDG","from_name":"label","to_name":"image","type":"rectanglelabels","origin":"manual"},{"original_width":3509,"original_height":2480,"image_rotation":0,"value":{"x":65.71699431194492,"y":53.67024280067759,"width":5.787845524398765,"height":2.5409373235460113,"rotation":0,"rectanglelabels":["total_additional_charges"]},"id":"Vnj7icDV6Z","from_name":"label","to_name":"image","type":"rectanglelabels","origin":"manual"},{"original_width":3509,"original_height":2480,"image_rotation":0,"value":{"x":74.29897215846721,"y":53.6702428006776,"width":4.889731563716217,"height":2.258610954263122,"rotation":0,"rectanglelabels":["total_ccl"]},"id":"hdpTiCibaC","from_name":"label","to_name":"image","type":"rectanglelabels","origin":"manual"},{"original_width":3509,"original_height":2480,"image_rotation":0,"value":{"x":81.5836742840036,"y":53.52907961603616,"width":5.48847420417124,"height":2.3997741389045713,"rotation":0,"rectanglelabels":["total_vat"]},"id":"BKdcXv4r5a","from_name":"label","to_name":"image","type":"rectanglelabels","origin":"manual"},{"original_width":3509,"original_height":2480,"image_rotation":0,"value":{"x":89.72158467218841,"y":53.55731225296444,"width":6.0872168446262895,"height":2.3997741389045713,"rotation":0,"rectanglelabels":["total_amount"]},"id":"cao0Gk48Mo","from_name":"label","to_name":"image","type":"rectanglelabels","origin":"manual"},{"original_width":3509,"original_height":2480,"image_rotation":0,"value":{"x":7.3545554335894625,"y":90.9937888198758,"width":85.94950603732161,"height":2.1739130434782594,"rotation":0,"rectanglelabels":["other"]},"id":"cQK-M2l6sP","from_name":"label","to_name":"image","type":"rectanglelabels","origin":"manual"}],"was_cancelled":false,"ground_truth":false,"created_at":"2023-12-18T04:41:28.894744Z","updated_at":"2023-12-18T15:46:39.360495Z","lead_time":485.6089999999999,"prediction":{},"result_count":0,"task":19,"parent_prediction":null,"parent_annotation":null}],"file_upload":"987fc69d-0008.jpg","drafts":[],"predictions":[],"data":{"image":"\/data\/upload\/4\/987fc69d-0008.jpg"},"meta":{},"created_at":"2023-12-18T04:15:16.433574Z","updated_at":"2023-12-18T15:46:39.382507Z","inner_id":2,"total_annotations":1,"cancelled_annotations":0,"total_predictions":0,"comment_count":0,"unresolved_comment_count":0,"last_comment_updated_at":null,"project":4,"updated_by":1,"comment_authors":[]},{"id":18,"annotations":[{"id":22,"completed_by":1,"result":[{"original_width":2480,"original_height":3509,"image_rotation":0,"value":{"x":5.273437500000002,"y":3.4482758620689644,"width":38.085937499999964,"height":8.275862068965509,"rotation":0,"rectanglelabels":["other"]},"id":"Nq7DnFg-gt","from_name":"label","to_name":"image","type":"rectanglelabels","origin":"manual"},{"original_width":2480,"original_height":3509,"image_rotation":0,"value":{"x":58.0078125,"y":0.9655172413793104,"width":37.89062499999991,"height":3.3103448275862055,"rotation":0,"rectanglelabels":["company_info"]},"id":"OWGWiGB4xn","from_name":"label","to_name":"image","type":"rectanglelabels","origin":"manual"},{"original_width":2480,"original_height":3509,"image_rotation":0,"value":{"x":10.866477272727277,"y":16.67711598746081,"width":27.69886363636365,"height":8.652037617554875,"rotation":0,"rectanglelabels":["other"]},"id":"5AKWa6RM1i","from_name":"label","to_name":"image","type":"rectanglelabels","origin":"manual"},{"original_width":2480,"original_height":3509,"image_rotation":0,"value":{"x":68.92755681818183,"y":21.191222570532915,"width":8.345170454545459,"height":1.5047021943573662,"rotation":0,"rectanglelabels":["account_number"]},"id":"sZODPPoz7K","from_name":"label","to_name":"image","type":"rectanglelabels","origin":"manual"},{"original_width":2480,"original_height":3509,"image_rotation":0,"value":{"x":68.69702643688956,"y":23.108111609109056,"width":8.51098797896318,"height":1.2435555325267489,"rotation":0,"rectanglelabels":["invoice_number"]},"id":"I68QnByqfK","from_name":"label","to_name":"image","type":"rectanglelabels","origin":"manual"},{"original_width":2480,"original_height":3509,"image_rotation":0,"value":{"x":68.75,"y":24.82758620689655,"width":9.5703125,"height":1.6551724137931034,"rotation":0,"rectanglelabels":["payment_due"]},"id":"9nS1PxgbkJ","from_name":"label","to_name":"image","type":"rectanglelabels","origin":"manual"},{"original_width":2480,"original_height":3509,"image_rotation":0,"value":{"x":68.75,"y":27.034482758620683,"width":9.5703125,"height":1.2413793103448276,"rotation":0,"rectanglelabels":["invoice_date"]},"id":"4tgoqlGUer","from_name":"label","to_name":"image","type":"rectanglelabels","origin":"manual"},{"original_width":2480,"original_height":3509,"image_rotation":0,"value":{"x":68.75,"y":28.551724137931036,"width":13.28125,"height":1.6551724137931034,"rotation":0,"rectanglelabels":["invoice_period"]},"id":"mE4rAqwmAs","from_name":"label","to_name":"image","type":"rectanglelabels","origin":"manual"},{"original_width":2480,"original_height":3509,"image_rotation":0,"value":{"x":68.75,"y":30.620689655172413,"width":13.28125,"height":1.3793103448275865,"rotation":0,"rectanglelabels":["vast_registion_number"]},"id":"jX3WhmFzNh","from_name":"label","to_name":"image","type":"rectanglelabels","origin":"manual"},{"original_width":2480,"original_height":3509,"image_rotation":0,"value":{"x":50.390625,"y":20.551724137931036,"width":17.578125,"height":12.275862068965518,"rotation":0,"rectanglelabels":["other"]},"id":"704FpCTc23","from_name":"label","to_name":"image","type":"rectanglelabels","origin":"manual"},{"original_width":2480,"original_height":3509,"image_rotation":0,"value":{"x":51.7578125,"y":5.379310344827586,"width":40.4296875,"height":7.724137931034483,"rotation":0,"rectanglelabels":["other"]},"id":"qehzpKW_2b","from_name":"label","to_name":"image","type":"rectanglelabels","origin":"manual"},{"original_width":2480,"original_height":3509,"image_rotation":0,"value":{"x":51.171875,"y":14.068965517241383,"width":31.0546875,"height":5.931034482758621,"rotation":0,"rectanglelabels":["other"]},"id":"gK0EV7TEj8","from_name":"label","to_name":"image","type":"rectanglelabels","origin":"manual"},{"original_width":2480,"original_height":3509,"image_rotation":0,"value":{"x":10.546875000000004,"y":33.241379310344826,"width":55.27343750000002,"height":11.999999999999975,"rotation":0,"rectanglelabels":["other"]},"id":"MhFshkqbCY","from_name":"label","to_name":"image","type":"rectanglelabels","origin":"manual"},{"original_width":2480,"original_height":3509,"image_rotation":0,"value":{"x":10.3515625,"y":46.06896551724138,"width":55.46875,"height":15.586206896551724,"rotation":0,"rectanglelabels":["other"]},"id":"EWCMRKr8Aw","from_name":"label","to_name":"image","type":"rectanglelabels","origin":"manual"},{"original_width":2480,"original_height":3509,"image_rotation":0,"value":{"x":66.6015625,"y":50.3448275862069,"width":26.7578125,"height":22.620689655172413,"rotation":0,"rectanglelabels":["other"]},"id":"PfUfm81shR","from_name":"label","to_name":"image","type":"rectanglelabels","origin":"manual"},{"original_width":2480,"original_height":3509,"image_rotation":0,"value":{"x":66.79687499999997,"y":34.758620689655174,"width":26.75781249999999,"height":15.172413793103447,"rotation":0,"rectanglelabels":["other"]},"id":"LFsf-NXHAd","from_name":"label","to_name":"image","type":"rectanglelabels","origin":"manual"},{"original_width":2480,"original_height":3509,"image_rotation":0,"value":{"x":11.914062499999995,"y":64.13793103448276,"width":19.3359375,"height":1.9310344827585968,"rotation":0,"rectanglelabels":["other"]},"id":"U6ZSIE_2Tj","from_name":"label","to_name":"image","type":"rectanglelabels","origin":"manual"},{"original_width":2480,"original_height":3509,"image_rotation":0,"value":{"x":51.171875,"y":63.86206896551724,"width":13.4765625,"height":2.206896551724138,"rotation":0,"rectanglelabels":["total_amount"]},"id":"zf1_3P9HCv","from_name":"label","to_name":"image","type":"rectanglelabels","origin":"manual"},{"original_width":2480,"original_height":3509,"image_rotation":0,"value":{"x":10.3515625,"y":93.51724137931032,"width":78.515625,"height":2.8965517241378995,"rotation":0,"rectanglelabels":["other"]},"id":"AlScUNj2Mx","from_name":"label","to_name":"image","type":"rectanglelabels","origin":"manual"}],"was_cancelled":false,"ground_truth":false,"created_at":"2023-12-18T04:25:41.519151Z","updated_at":"2023-12-18T15:46:24.569617Z","lead_time":635.772,"prediction":{},"result_count":0,"task":18,"parent_prediction":null,"parent_annotation":null}],"file_upload":"12e9f720-0001.jpg","drafts":[],"predictions":[],"data":{"image":"\/data\/upload\/4\/12e9f720-0001.jpg"},"meta":{},"created_at":"2023-12-18T04:15:16.433574Z","updated_at":"2023-12-18T15:46:24.594614Z","inner_id":1,"total_annotations":1,"cancelled_annotations":0,"total_predictions":0,"comment_count":0,"unresolved_comment_count":0,"last_comment_updated_at":null,"project":4,"updated_by":1,"comment_authors":[]},{"id":21,"annotations":[{"id":25,"completed_by":1,"result":[{"original_width":2480,"original_height":3509,"image_rotation":0,"value":{"x":3.7109375,"y":1.5172413793103448,"width":39.6484375,"height":10.896551724137934,"rotation":0,"rectanglelabels":["other"]},"id":"c714qly5q3","from_name":"label","to_name":"image","type":"rectanglelabels","origin":"manual"},{"original_width":2480,"original_height":3509,"image_rotation":0,"value":{"x":58.203125,"y":0.8275862068965513,"width":37.70489069650294,"height":4.275862068965512,"rotation":0,"rectanglelabels":["company_info"]},"id":"G1k3CoEjPT","from_name":"label","to_name":"image","type":"rectanglelabels","origin":"manual"},{"original_width":2480,"original_height":3509,"image_rotation":0,"value":{"x":81.37464995560397,"y":6.50040392002613,"width":9.338074585068835,"height":1.7899662968188461,"rotation":0,"rectanglelabels":["account_number"]},"id":"cv-0x2UloB","from_name":"label","to_name":"image","type":"rectanglelabels","origin":"manual"},{"original_width":2480,"original_height":3509,"image_rotation":0,"value":{"x":81.28755339217773,"y":8.68355550605486,"width":9.866166406350105,"height":1.3025722551447816,"rotation":0,"rectanglelabels":["invoice_date"]},"id":"rTTq4SEJWN","from_name":"label","to_name":"image","type":"rectanglelabels","origin":"manual"},{"original_width":2480,"original_height":3509,"image_rotation":0,"value":{"x":82.1353667754031,"y":10.287050759773146,"width":7.6071681979903545,"height":1.6350279353281802,"rotation":0,"rectanglelabels":["page"]},"id":"vZA-krcM1k","from_name":"label","to_name":"image","type":"rectanglelabels","origin":"manual"},{"original_width":2480,"original_height":3509,"image_rotation":0,"value":{"x":68.24401615298594,"y":6.082693211786394,"width":12.67861366331719,"height":6.54011174131272,"rotation":0,"rectanglelabels":["other"]},"id":"5j4qcNxBJs","from_name":"label","to_name":"image","type":"rectanglelabels","origin":"manual"},{"original_width":2480,"original_height":3509,"image_rotation":0,"value":{"x":9.812144487262914,"y":15.425709985090279,"width":11.686374333144602,"height":7.941564257308302,"rotation":0,"rectanglelabels":["other"]},"id":"x4TnSAYV1U","from_name":"label","to_name":"image","type":"rectanglelabels","origin":"manual"},{"original_width":2480,"original_height":3509,"image_rotation":0,"value":{"x":21.939514078262025,"y":15.737143877533738,"width":13.009360106708106,"height":1.635027935328177,"rotation":0,"rectanglelabels":["invoice_period"]},"id":"SqotmBdEPe","from_name":"label","to_name":"image","type":"rectanglelabels","origin":"manual"},{"original_width":2480,"original_height":3509,"image_rotation":0,"value":{"x":22.16001170718929,"y":17.683605705305396,"width":20.837025933625753,"height":1.5571694622173182,"rotation":0,"rectanglelabels":["product_name"]},"id":"kgUCr0tvgq","from_name":"label","to_name":"image","type":"rectanglelabels","origin":"manual"},{"original_width":2480,"original_height":3509,"image_rotation":0,"value":{"x":21.939514078262036,"y":19.47435058685531,"width":11.906871962071857,"height":1.635027935328183,"rotation":0,"rectanglelabels":["charge_type"]},"id":"rex3oiGye9","from_name":"label","to_name":"image","type":"rectanglelabels","origin":"manual"},{"original_width":2480,"original_height":3509,"image_rotation":0,"value":{"x":21.82926526379841,"y":21.187236995294356,"width":11.906871962071857,"height":5.216517698428008,"rotation":0,"rectanglelabels":["site_address"]},"id":"gljmRevQDu","from_name":"label","to_name":"image","type":"rectanglelabels","origin":"manual"},{"original_width":2480,"original_height":3509,"image_rotation":0,"value":{"x":48.840224807387344,"y":15.192134565757692,"width":46.52499970365115,"height":13.936666686844978,"rotation":0,"rectanglelabels":["other"]},"id":"Yu0_TGLFbU","from_name":"label","to_name":"image","type":"rectanglelabels","origin":"manual"},{"original_width":2480,"original_height":3509,"image_rotation":0,"value":{"x":3.638210877299709,"y":29.20665972571353,"width":92.2782577060563,"height":18.60817507349674,"rotation":0,"rectanglelabels":["other"]},"id":"AST4_9zjcj","from_name":"label","to_name":"image","type":"rectanglelabels","origin":"manual"},{"original_width":2480,"original_height":3509,"image_rotation":0,"value":{"x":5.402191908717787,"y":50.15058899253643,"width":7.82766582691761,"height":2.102178773993383,"rotation":0,"rectanglelabels":["other"]},"id":"vm77ySV40y","from_name":"label","to_name":"image","type":"rectanglelabels","origin":"manual"},{"original_width":2480,"original_height":3509,"image_rotation":0,"value":{"x":84.34034306467566,"y":49.83915510009298,"width":10.363388559581066,"height":2.1021787739933675,"rotation":0,"rectanglelabels":["total_amount"]},"id":"HmQI64KlVx","from_name":"label","to_name":"image","type":"rectanglelabels","origin":"manual"}],"was_cancelled":false,"ground_truth":false,"created_at":"2023-12-18T07:05:23.688417Z","updated_at":"2023-12-18T07:19:55.429541Z","lead_time":318.87399999999997,"prediction":{},"result_count":0,"task":21,"parent_prediction":null,"parent_annotation":null}],"file_upload":"d9c53649-0010.jpg","drafts":[],"predictions":[],"data":{"image":"\/data\/upload\/4\/d9c53649-0010.jpg"},"meta":{},"created_at":"2023-12-18T04:15:16.433574Z","updated_at":"2023-12-18T07:19:55.451874Z","inner_id":4,"total_annotations":1,"cancelled_annotations":0,"total_predictions":0,"comment_count":0,"unresolved_comment_count":0,"last_comment_updated_at":null,"project":4,"updated_by":1,"comment_authors":[]}]